

{
 "planningWindow": "500",
 "numOfSattelites": "2",
 "numOfUsers": "4",
 "numOfRequestsPerUser": "1",
 "numOfObservationsPerRequest": "2",
 "satellites": [
{
  "id": "0",
  "capacity": "8",
  "orbitStartTime": "0",
  "orbitEndTime": "500"
},
{
  "id": "1",
  "capacity": "8",
  "orbitStartTime": "0",
  "orbitEndTime": "500"
},
],
 "users": [
{
  "id": "0",
 "requests": [
{
  "id": "0",
 "observations": [
{
  "id": "0",
  "reward": "10",
  "satellateId": "1",
  "startTime": "372",
  "endTime": "384"
},
{
  "id": "1",
  "reward": "38",
  "satellateId": "1",
  "startTime": "393",
  "endTime": "405"
},
],
},
],
},
{
  "id": "1",
 "requests": [
{
  "id": "0",
 "observations": [
{
  "id": "0",
  "reward": "13",
  "satellateId": "0",
  "startTime": "437",
  "endTime": "450"
},
{
  "id": "1",
  "reward": "45",
  "satellateId": "1",
  "startTime": "461",
  "endTime": "471"
},
],
},
],
},
{
  "id": "2",
 "requests": [
{
  "id": "0",
 "observations": [
{
  "id": "0",
  "reward": "19",
  "satellateId": "1",
  "startTime": "203",
  "endTime": "218"
},
{
  "id": "1",
  "reward": "37",
  "satellateId": "0",
  "startTime": "230",
  "endTime": "243"
},
],
},
],
},
{
  "id": "3",
 "requests": [
{
  "id": "0",
 "observations": [
{
  "id": "0",
  "reward": "36",
  "satellateId": "1",
  "startTime": "42",
  "endTime": "53"
},
{
  "id": "1",
  "reward": "38",
  "satellateId": "1",
  "startTime": "125",
  "endTime": "137"
},
],
},
],
},
],
}
